co2gui/__init__.py
co2gui/__main__.py
co2gui/tkdialog.py
co2gui/icons/CO2MPAS_banner2.png
co2gui/icons/CO2MPAS_icon-64.png
co2gui/icons/add_file-olive-32.png
co2gui/icons/add_folder-olive-32.png
co2gui/icons/align_center-olive-16.png
co2gui/icons/align_center-olive-32.png
co2gui/icons/car-olive-16.png
co2gui/icons/dice-orange-16.png
co2gui/icons/dice-orange-32.png
co2gui/icons/download-olive-32.png
co2gui/icons/download_dir-olive-32.png
co2gui/icons/excel-olive-16.png
co2gui/icons/excel-olive-32.png
co2gui/icons/file-olive-16.png
co2gui/icons/folder-olive-16.png
co2gui/icons/gear-olive-16.png
co2gui/icons/hand-red-32.png
co2gui/icons/help-olive-32.png
co2gui/icons/play-olive-32.png
co2gui/icons/play_doc-orange-32.png
co2gui/icons/shield-orange-32.png
co2gui/icons/to_dice-orange-32.png
co2gui/icons/trash-olive-32.png
co2gui-3.0.0.dist-info/METADATA
co2gui-3.0.0.dist-info/RECORD
co2gui-3.0.0.dist-info/WHEEL
co2gui-3.0.0.dist-info/entry_points.txt
co2gui-3.0.0.dist-info/top_level.txt
co2gui-3.0.0.dist-info/zip-safe
