Metadata-Version: 2.1
Name: co2gui
Version: 3.0.0
Summary: Polyvers's lib to derive subproject versions from tags on Git monorepos.
Home-page: https://co2mpas.io/
Author: CO2MPAS-Team
Author-email: JRC-CO2MPAS@ec.europa.eu
License: EUPL 1.1+
Download-URL: https://pypi.org/project/co2gui/
Project-URL: Documentation, Https://co2mpas.io
Project-URL: Source, https://github.com/JRCSTU/CO2MPAS-TA
Project-URL: Tracker, https://github.com/JRCSTU/CO2MPAS-TA/issues
Keywords: CO2,fuel-consumption,WLTP,NEDC,vehicle,automotive,EU,JRC,IET,STU,correlation,back-translation,policy,monitoring,M1,N1,simulator,engineering,scientific
Platform: any
Classifier: Programming Language :: Python
Classifier: Programming Language :: Python :: 3
Classifier: Programming Language :: Python :: 3.5
Classifier: Programming Language :: Python :: 3.6
Classifier: Programming Language :: Python :: 3.7
Classifier: Programming Language :: Python :: Implementation :: CPython
Classifier: Development Status :: 4 - Beta
Classifier: Natural Language :: English
Classifier: Intended Audience :: Developers
Classifier: Intended Audience :: Science/Research
Classifier: Intended Audience :: Manufacturing
Classifier: Environment :: Console
Classifier: License :: OSI Approved :: European Union Public Licence 1.1 (EUPL 1.1)
Classifier: Natural Language :: English
Classifier: Operating System :: MacOS :: MacOS X
Classifier: Operating System :: Microsoft :: Windows
Classifier: Operating System :: POSIX
Classifier: Operating System :: Unix
Classifier: Operating System :: OS Independent
Classifier: Topic :: Scientific/Engineering
Classifier: Topic :: Scientific/Engineering :: Information Analysis
Obsoletes: co2mpas (< 2.0)
Requires-Python: >=3.5
Provides-Extra: test
Requires-Dist: polyversion (>=0.2.2a0)
Requires-Dist: co2sim[io]
Requires-Dist: co2dice
Requires-Dist: Pillow
Requires-Dist: numpy
Requires-Dist: pandalone[xlrd] (>=0.2.0)
Requires-Dist: schema
Requires-Dist: PyYAML (>=3.12)
Requires-Dist: boltons
Requires-Dist: toolz
Requires-Dist: schedula[plot] (>=0.2.3)
Provides-Extra: test
Requires-Dist: pytest; extra == 'test'
Requires-Dist: pytest-runner; extra == 'test'
Requires-Dist: flake8; extra == 'test'
Requires-Dist: flake8-builtins; extra == 'test'
Requires-Dist: flake8-mutable; extra == 'test'
Requires-Dist: ddt; extra == 'test'
